mpesa/__init__.py
mpesa/api/__init__.py
mpesa/api/auth.py
mpesa/api/b2b.py
mpesa/api/b2c.py
mpesa/api/balance.py
mpesa/api/c2b.py
mpesa/api/mpesa_express.py
mpesa/api/reversal.py
mpesa/api/transaction_status.py
mpesa/tests/__init__.py
mpesa/tests/test_auth.py
mpesa/tests/test_b2b.py
mpesa/tests/test_b2c.py
mpesa/tests/test_balance.py
mpesa/tests/test_c2b.py
mpesa/tests/test_mpesa_express.py
mpesa/tests/test_reversal.py
mpesa/tests/test_transaction_status.py
mpesa_daraja-0.0.23.dist-info/LICENSE
mpesa_daraja-0.0.23.dist-info/METADATA
mpesa_daraja-0.0.23.dist-info/WHEEL
mpesa_daraja-0.0.23.dist-info/top_level.txt
mpesa_daraja-0.0.23.dist-info/RECORD
