Metadata-Version: 2.1
Name: mpesa-daraja
Version: 0.0.23
Summary: Mpesa B2C, C2B, STKPush Python(Flask & Django) library based on the new Api's https://developer.safaricom.co.ke
Home-page: https://github.com/cephaske254/mpesa_daraja
Author: Cephas Too
Author-email: cephaske254@gmail.com
License: MIT
Platform: UNKNOWN
Classifier: Programming Language :: Python
Classifier: License :: OSI Approved :: MIT License
Classifier: Operating System :: OS Independent
Requires-Python: >=3.0
Requires-Dist: certifi (>=2019.11.28)
Requires-Dist: chardet (>=3.0.4)
Requires-Dist: idna (>=2.8)
Requires-Dist: pytest (>=3.6.1)
Requires-Dist: requests (>=2.22.0)
Requires-Dist: six (>=1.14.0)
Requires-Dist: urllib3 (>=1.25.8)
Requires-Dist: webencodings (>=0.5.1)
